multigen/__init__.py
multigen/formatter.py
multigen/generator.py
multigen/jinja.py
pymultigen-0.1.1.dist-info/DESCRIPTION.rst
pymultigen-0.1.1.dist-info/METADATA
pymultigen-0.1.1.dist-info/RECORD
pymultigen-0.1.1.dist-info/WHEEL
pymultigen-0.1.1.dist-info/metadata.json
pymultigen-0.1.1.dist-info/top_level.txt
