Metadata-Version: 2.0
Name: pymultigen
Version: 0.1.1
Summary: Multi-file frontend for single-file code generators.
Home-page: https://github.com/moltob/pymultigen
Author: Mike Pagel
Author-email: mike@mpagel.de
License: MIT License
Keywords: code generator jinja multi-file
Platform: UNKNOWN
Classifier: Development Status :: 4 - Beta
Classifier: Programming Language :: Python
Classifier: Programming Language :: Python :: 3 :: Only
Classifier: Operating System :: OS Independent
Classifier: Intended Audience :: Developers
Classifier: Topic :: Software Development
Classifier: Topic :: Software Development :: Libraries
Classifier: License :: OSI Approved :: MIT License
